unity_test_parser.py
unity_test_parser-0.1.1.dist-info/LICENSE
unity_test_parser-0.1.1.dist-info/METADATA
unity_test_parser-0.1.1.dist-info/WHEEL
unity_test_parser-0.1.1.dist-info/top_level.txt
unity_test_parser-0.1.1.dist-info/RECORD
