Metadata-Version: 2.1
Name: unity-test-parser
Version: 0.1.1
Summary: Parse the output of the Unity Test Framework for C
Home-page: https://github.com/ETCLabs/unity-test-parser
Author: Sam Kearney
Author-email: sam.kearney@etcconnect.com
License: Apache 2.0
Platform: UNKNOWN
Classifier: License :: OSI Approved :: Apache Software License
Classifier: Programming Language :: Python
Classifier: Programming Language :: Python :: 3
Classifier: Development Status :: 3 - Alpha
Requires-Python: >=3
Requires-Dist: junit-xml (>=1.8)
